Metadata-Version: 2.1
Name: vk-api-rucod
Version: 1.0.2
Summary: Library for create vk bots on Python
Author: RuCodinger
Author-email: rucodinger@gmail.com
